sanskrit_tagger/__init__.py
sanskrit_tagger/device_util.py
sanskrit_tagger/pos_tagger.py
sanskrit_tagger/tagger_factory.py
sanskrit_tagger/data/char2id_42_734.dat
sanskrit_tagger/data/unique_tags_42_734.dat
sanskrit_tagger-0.1.5.dist-info/licenses/LICENSE
sanskrit_tagger-0.1.5.dist-info/METADATA
sanskrit_tagger-0.1.5.dist-info/WHEEL
sanskrit_tagger-0.1.5.dist-info/top_level.txt
sanskrit_tagger-0.1.5.dist-info/RECORD
