Metadata-Version: 2.4
Name: sanskrit_tagger
Version: 0.1.5
Summary: Pos tagger tools to use with pas taggers models
Home-page: https://github.com/koleslena/sanskrit_pos_tagger
Author: koleslena
Author-email: 
License: GNU GENERAL PUBLIC LICENSE
Keywords: sanskrit samskritam pos tagger pos-tagger nlp
Classifier: Development Status :: 3 - Alpha
Classifier: Intended Audience :: Education
Classifier: Intended Audience :: Science/Research
Classifier: Intended Audience :: Developers
Classifier: Topic :: Text Processing :: Linguistic
Classifier: License :: OSI Approved :: GNU General Public License (GPL)
Classifier: Programming Language :: Python :: 3
License-File: LICENSE
Requires-Dist: torch
Requires-Dist: numpy
Requires-Dist: tqdm
Provides-Extra: test
Requires-Dist: pytest; extra == "test"
Dynamic: author
Dynamic: classifier
Dynamic: home-page
Dynamic: keywords
Dynamic: license
Dynamic: license-file
Dynamic: provides-extra
Dynamic: requires-dist
Dynamic: summary
